README.rst
datasift_preview_grabber.py
setup.py
datasift_preview_grabber.egg-info/PKG-INFO
datasift_preview_grabber.egg-info/SOURCES.txt
datasift_preview_grabber.egg-info/dependency_links.txt
datasift_preview_grabber.egg-info/entry_points.txt
datasift_preview_grabber.egg-info/requires.txt
datasift_preview_grabber.egg-info/top_level.txt
test/test_datasift_preview_grabber.py