Metadata-Version: 1.1
Name: datasift-preview-grabber
Version: 0.0.0
Summary: Grabs Datasift preview stats and writes them out to stdout
Home-page: https://github.com/adaptivelab/datasift-preview-grabber
Author: Adaptive Lab
Author-email: hey@adaptivelab.com
License: GPLv3
Download-URL: https://github.com/adaptivelab/datasift-preview-grabber
Platform: UNKNOWN
